__init__.py
simtissue/__init__.py
simtissue/arbitrary_shape.py
simtissue/control_expression.py
simtissue/plot.py
simtissue/tissue.py
simtissue/utils.py
SimTissue-0.0.3.dist-info/LICENSE
SimTissue-0.0.3.dist-info/METADATA
SimTissue-0.0.3.dist-info/WHEEL
SimTissue-0.0.3.dist-info/top_level.txt
SimTissue-0.0.3.dist-info/RECORD
